jinja_renderer/__init__.py
jinja_renderer/__main__.py
dd_jinja_renderer-1.0.4.dist-info/METADATA
dd_jinja_renderer-1.0.4.dist-info/WHEEL
dd_jinja_renderer-1.0.4.dist-info/dependency_links.txt
dd_jinja_renderer-1.0.4.dist-info/entry_points.txt
dd_jinja_renderer-1.0.4.dist-info/top_level.txt
dd_jinja_renderer-1.0.4.dist-info/RECORD
