Metadata-Version: 2.1
Name: dd-jinja-renderer
Version: 1.0.4
Summary: A command line tool to generate jinja templates
Home-page: https://bitbucket.org/dataductus/jinja-renderer
Author: Calle Holst
Author-email: dummy@dataductus.se
License: MIT
Download-URL: https://bitbucket.org/dataductus/jinja-renderer/1.0.0.tar.gz
Platform: UNKNOWN
Classifier: License :: OSI Approved :: MIT License
Classifier: Programming Language :: Python :: 2.7
Classifier: Programming Language :: Python :: 3
Classifier: Programming Language :: Python :: 3.7
Requires-Python: >=3.4
Requires-Dist: jinja2
Requires-Dist: argparse
